pyreft/__init__.py
pyreft/config.py
pyreft/dataset.py
pyreft/interventions.py
pyreft/mapping.py
pyreft/reft_model.py
pyreft/reft_trainer.py
pyreft/utils.py
pyreft-0.1.0.dist-info/LICENSE
pyreft-0.1.0.dist-info/METADATA
pyreft-0.1.0.dist-info/WHEEL
pyreft-0.1.0.dist-info/top_level.txt
pyreft-0.1.0.dist-info/RECORD
