Metadata-Version: 2.2
Name: pyreft
Version: 0.1.0
Summary: REFT: Representation Finetuning for Language Models
Home-page: https://github.com/stanfordnlp/pyreft
Author: Zhengxuan Wu
Author-email: wuzhengx@stanford.edu
License: Apache License 2.0
Classifier: Development Status :: 3 - Alpha
Classifier: Intended Audience :: Science/Research
Classifier: License :: OSI Approved :: MIT License
Classifier: Operating System :: POSIX :: Linux
Classifier: Programming Language :: Python :: 3
Classifier: Programming Language :: Python :: 3.8
Classifier: Programming Language :: Python :: 3.9
Requires-Python: >=3.8
License-File: LICENSE
Requires-Dist: torch>=2.0.0
Requires-Dist: pyvene>=0.1.7
Requires-Dist: transformers==4.45.1
Requires-Dist: protobuf>=3.20.0
Requires-Dist: matplotlib>=3.7.4
Requires-Dist: ipywidgets>=8.1.1
Requires-Dist: plotnine>=0.12.4
Requires-Dist: huggingface-hub
Requires-Dist: numpy>=1.26.4
Requires-Dist: accelerate>=0.29.1
Requires-Dist: sentencepiece>=0.1.96
Requires-Dist: evaluate>=0.4.1
Requires-Dist: datasets>=2.18.0
Requires-Dist: wandb
Requires-Dist: scikit-learn
Requires-Dist: jupyter
Requires-Dist: fsspec>=2024.2.0
Requires-Dist: ydata-profiling>=4.7.0
Requires-Dist: seaborn==0.12.2
Requires-Dist: gcsfs>=2024.2.0
Dynamic: author
Dynamic: author-email
Dynamic: classifier
Dynamic: description
Dynamic: description-content-type
Dynamic: home-page
Dynamic: license
Dynamic: requires-dist
Dynamic: requires-python
Dynamic: summary
